pintdantic/__init__.py
pintdantic/model.py
pintdantic/py.typed
pintdantic/types.py
pintdantic/utils.py
pintdantic-0.0.4.dist-info/licenses/LICENSE
pintdantic-0.0.4.dist-info/METADATA
pintdantic-0.0.4.dist-info/WHEEL
pintdantic-0.0.4.dist-info/top_level.txt
pintdantic-0.0.4.dist-info/RECORD
