Metadata-Version: 2.4
Name: pintdantic
Version: 0.0.4
Summary: Pydantic bindings for Pint
Author-email: Peter Pak <ppak10@gmail.com>
Requires-Python: >=3.10
License-File: LICENSE
Requires-Dist: pint>=0.24.4
Requires-Dist: pydantic>=2.11.9
Dynamic: license-file
